TwinPycs/__init__.py
TwinPycs/__main__.py
TwinPycs/A/__init__.py
TwinPycs/A/main.py
TwinPycs/B/__init__.py
TwinPycs/B/helper.py
twinpycs-0.1.0.dist-info/METADATA
twinpycs-0.1.0.dist-info/WHEEL
twinpycs-0.1.0.dist-info/entry_points.txt
twinpycs-0.1.0.dist-info/top_level.txt
twinpycs-0.1.0.dist-info/RECORD
