Metadata-Version: 2.4
Name: TwinPycs
Version: 0.1.0
Summary: A sample package with wxPython message box
Author-email: Your Name <your.email@example.com>
Classifier: Programming Language :: Python :: 3
Classifier: Operating System :: Microsoft :: Windows
Requires-Python: >=3.8
Requires-Dist: wxPython>=4.2.1
Requires-Dist: numpy>=1.26.0
Requires-Dist: h5py>=3.10.0
